{
	"name": "Vanessa",
	"type" : "human",
	"start": "00",
	"passages": {
		"00": {
			"text": "Vanessa: Haiii! How are you?",
			"links": [
				{
					"text": "Good Morning!",
					"link": "01"
				},
				{
					"text": "The moon is beautiful tonight.",
					"link": "02"
				},
				{
					"text": "Compliment her eyes",
					"link": "03"
				}
			]
		},
		"01": {
			"text": "Vanessa: Its nighttime silly.",
			"execute": "smirk",
			"links": [
				{
					"text": "Continue",
					"link": "04"
				}
			]
		},
		 "02": {
			"text": "I know, really puts you in the halloween spirit, huh.",
			"links": [
				{
					"text": "Continue",
					"link": "04"
				}
			]
		},
		"03": {
			"text": "Vanessa: Thanks! I love wearing colored contacts.",
			"links": [
				{
					"text": "Continue",
					"link": "04"
				}
			]
		},
		"04": {
			"text": "Thanks."
		}
	}
}
